webviz_config_equinor/__init__.py
webviz_config_equinor/assets/equinor_logo_symbol.svg
webviz_config_equinor/assets/equinor_theme.css
webviz_config_equinor/assets/favicon.ico
webviz_config_equinor-0.2.6.dist-info/METADATA
webviz_config_equinor-0.2.6.dist-info/WHEEL
webviz_config_equinor-0.2.6.dist-info/entry_points.txt
webviz_config_equinor-0.2.6.dist-info/top_level.txt
webviz_config_equinor-0.2.6.dist-info/RECORD
