Metadata-Version: 2.1
Name: webviz-config-equinor
Version: 0.2.6
Summary: Webviz config Equinor theme
Home-page: https://github.com/equinor/webviz-config-equinor
Author: R&T Equinor
Classifier: Programming Language :: Python :: 3
Classifier: Operating System :: OS Independent
Classifier: Natural Language :: English
Classifier: Topic :: Multimedia :: Graphics
Classifier: Topic :: Scientific/Engineering
Classifier: Topic :: Scientific/Engineering :: Visualization
Classifier: License :: Other/Proprietary License
Requires-Python: ~=3.8
Requires-Dist: plotly>=5.0
Requires-Dist: webviz-config>=0.0.48
Provides-Extra: tests
Requires-Dist: black; extra == "tests"
